README.md
setup.py
social_scrape/__init__.py
social_scrape/cli.py
social_scrape/insta_scrape.py
social_scrape/twitter_scrape.py
social_scrape.egg-info/PKG-INFO
social_scrape.egg-info/SOURCES.txt
social_scrape.egg-info/dependency_links.txt
social_scrape.egg-info/entry_points.txt
social_scrape.egg-info/not-zip-safe
social_scrape.egg-info/requires.txt
social_scrape.egg-info/top_level.txt